{
  "ok": true,
  "date": "2026-03-28",
  "source": "local-official-scraper",
  "automatedAirlines": [
    "EK",
    "QR"
  ],
  "manualAirlines": [
    "GF",
    "AI"
  ],
  "airlines": {
    "EK": {
      "isLive": false,
      "error": "The Emirates official source did not include the tracked flight for the requested date.",
      "code": "tracked_flights_missing",
      "source": "Emirates official flight status"
    },
    "QR": {
      "isLive": true,
      "source": "Qatar Airways official flight status",
      "requestedDate": "2026-03-28",
      "resolvedDate": "2026-03-28",
      "leg1FlightNumber": "QR573",
      "leg1Status": "delayed",
      "leg1Delay": 10,
      "leg1DepActual": "09:33",
      "leg1ArrActual": "11:40",
      "leg1ScheduledDep": "09:25",
      "leg1ScheduledArr": "11:30",
      "leg1EstimatedDep": "09:33",
      "leg1EstimatedArr": "11:29",
      "leg1DepDisplay": "09:33",
      "leg1ArrDisplay": "11:40",
      "leg1DepLabel": "Actual departure",
      "leg1ArrLabel": "Actual arrival",
      "leg1Duration": "4h35m",
      "leg1TimeLeft": null,
      "leg1RawStatus": "ARRIVED",
      "leg1RawStatusCode": "ARVD",
      "leg1SourceUrl": "https://fs.qatarairways.com/flightstatus/search",
      "leg1Missing": false,
      "leg2FlightNumber": "No connection",
      "leg2Status": "unknown",
      "leg2Delay": 0,
      "leg2DepActual": null,
      "leg2ArrActual": null,
      "leg2ScheduledDep": null,
      "leg2ScheduledArr": null,
      "leg2EstimatedDep": null,
      "leg2EstimatedArr": null,
      "leg2DepDisplay": null,
      "leg2ArrDisplay": null,
      "leg2DepLabel": "No departure",
      "leg2ArrLabel": "No arrival",
      "leg2Duration": null,
      "leg2TimeLeft": null,
      "leg2RawStatus": "No viable onward flight published",
      "leg2RawStatusCode": null,
      "leg2SourceUrl": null,
      "leg2Missing": true,
      "layoverScheduledMinutes": null,
      "layoverActualMinutes": 0,
      "minimumLayoverMinutes": 90,
      "connectionPossible": false,
      "connectionReason": "No DOH-FRA departure is published after QR573 arrives in Doha.",
      "notes": [
        "QR573: ARRIVED",
        "No onward connection published",
        "Available DOH-FRA results: QR069 CANCELLED, QR067 CANCELLED"
      ]
    },
    "GF": {
      "isLive": false,
      "unsupported": true,
      "error": "No free automated local scraper is implemented for GF yet."
    },
    "AI": {
      "isLive": false,
      "unsupported": true,
      "error": "No free automated local scraper is implemented for AI yet."
    }
  },
  "snapshotGeneratedAt": "2026-03-28T12:11:14.171Z",
  "pagesUrl": "https://vikrantsingh29.github.io/flightSearch/"
}